job_processing/__init__.py
job_processing/methods/Modied_FBLPT.py
job_processing/methods/Modified_FBLPT.py
job_processing/methods/__init__.py
job_processing/models/Batch.py
job_processing/models/Job.py
job_processing/models/Machine.py
job_processing/models/__init__.py
job_processing-0.0.4.dist-info/METADATA
job_processing-0.0.4.dist-info/WHEEL
job_processing-0.0.4.dist-info/top_level.txt
job_processing-0.0.4.dist-info/RECORD
