Metadata-Version: 2.1
Name: job-processing
Version: 0.0.4
Summary: Job Processing Package
Author: Dominik Sebesic
Author-email: <sebesic.dominik@email.com>
Keywords: python,job processing
Classifier: Development Status :: 3 - Alpha
Classifier: Intended Audience :: Education
Classifier: Programming Language :: Python :: 2
Classifier: Programming Language :: Python :: 3
Classifier: Operating System :: MacOS :: MacOS X
Classifier: Operating System :: Microsoft :: Windows
